colbert_server/__init__.py
colbert_server/__main__.py
colbert_server/data.py
colbert_server/server.py
colbert_server-0.3.1.dist-info/WHEEL
colbert_server-0.3.1.dist-info/entry_points.txt
colbert_server-0.3.1.dist-info/METADATA
colbert_server-0.3.1.dist-info/RECORD
