Metadata-Version: 2.4
Name: colbert-server
Version: 0.3.1
Summary: Run ColBERT Wikipedia server
Keywords: colbert,retrieval,search,wikipedia,ir
Author: Niels van Galen Last
Author-email: Niels van Galen Last <nvangalenlast@gmail.com>
License-Expression: MIT
Classifier: Development Status :: 4 - Beta
Classifier: Intended Audience :: Developers
Classifier: License :: OSI Approved :: MIT License
Classifier: Programming Language :: Python :: 3
Classifier: Programming Language :: Python :: 3.13
Classifier: Operating System :: OS Independent
Classifier: Topic :: Scientific/Engineering :: Information Analysis
Classifier: Topic :: Internet :: WWW/HTTP :: Indexing/Search
Requires-Dist: colbert-ai>=0.2.22
Requires-Dist: faiss-cpu>=1.12.0
Requires-Dist: flask>=3.1.2
Requires-Dist: huggingface-hub>=0.36.0
Requires-Dist: packaging>=24.1
Requires-Dist: torch>=2.9.0
Requires-Python: >=3.13
Project-URL: Dataset, https://huggingface.co/datasets/nielsgl/colbert-wiki2017
Project-URL: Homepage, https://github.com/nielsgl/colbert-server
Project-URL: Issues, https://github.com/nielsgl/colbert-server/issues
Project-URL: Repository, https://github.com/nielsgl/colbert-server
